pyuca/__init__.py
pyuca/allkeys-10.0.0.txt
pyuca/allkeys-5.2.0.txt
pyuca/allkeys-6.3.0.txt
pyuca/allkeys-8.0.0.txt
pyuca/allkeys-9.0.0.txt
pyuca/collator.py
pyuca/trie.py
pyuca/utils.py
pyuca-1.2.dist-info/DESCRIPTION.rst
pyuca-1.2.dist-info/METADATA
pyuca-1.2.dist-info/RECORD
pyuca-1.2.dist-info/WHEEL
pyuca-1.2.dist-info/metadata.json
pyuca-1.2.dist-info/top_level.txt
