Metadata-Version: 1.1
Name: pyuca
Version: 1.2
Summary: a Python implementation of the Unicode Collation Algorithm
Home-page: http://github.com/jtauber/pyuca
Author: James Tauber
Author-email: jtauber@jtauber.com
License: MIT
Platform: UNKNOWN
Classifier: Development Status :: 5 - Production/Stable
Classifier: License :: OSI Approved :: MIT License
Classifier: Programming Language :: Python :: 2.7
Classifier: Programming Language :: Python :: 3.3
Classifier: Programming Language :: Python :: 3.4
Classifier: Programming Language :: Python :: 3.5
Classifier: Programming Language :: Python :: 3.6
Classifier: Topic :: Text Processing
